{
  "posts": [
    {
      "slug": "post1",
      "title": "Automating Notion with Siri Shortcuts",
      "date": "2024-07-20",
      "excerpt": "Learn how to connect Notion and Siri Shortcuts for powerful automations."
    },
    {
      "slug": "post2",
      "title": "Top Notion Automation Ideas for Beginners",
      "date": "2024-07-18",
      "excerpt": "A roundup of easy automation ideas to get started with Notion."
    },
    {
      "slug": "post3",
      "title": "Reusable shortcuts for Notion",
      "date": "2025-07-18",
      "excerpt": "Explore the way to speed the shortcut creation process."
    }
  ]
} 